agent_exchange/__init__.py
agent_exchange/agent.py
agent_exchange/exchange.py
agent_exchange-0.0.6.dist-info/LICENSE
agent_exchange-0.0.6.dist-info/METADATA
agent_exchange-0.0.6.dist-info/WHEEL
agent_exchange-0.0.6.dist-info/top_level.txt
agent_exchange-0.0.6.dist-info/RECORD
