Metadata-Version: 2.1
Name: agent-exchange
Version: 0.0.6
Summary: Tool to simulate multi-agent interactions in competitive environments
Home-page: https://github.com/maxholloway/agent-exchange
Author: Max Holloway
Author-email: maxwellpearmanholloway@gmail.com
License: UNKNOWN
Platform: UNKNOWN
Classifier: Programming Language :: Python :: 3
Classifier: License :: OSI Approved :: MIT License
Classifier: Operating System :: OS Independent
Requires-Dist: numpy (==1.19.2)
Requires-Dist: pandas (==1.1.3)
